movebank_client/__init__.py
movebank_client/cli.py
movebank_client/client.py
movebank_client/enums.py
movebank_client/errors.py
movebank_client/settings.py
movebank_client-1.2.0.dist-info/LICENSE
movebank_client-1.2.0.dist-info/METADATA
movebank_client-1.2.0.dist-info/WHEEL
movebank_client-1.2.0.dist-info/RECORD
