Metadata-Version: 2.3
Name: movebank-client
Version: 1.2.0
Summary: An async client for Movebank's API
License: Apache-2.0
Author: Chris Doehring
Author-email: chrisdo@earthranger.com
Requires-Python: >=3.7,<4.0
Classifier: License :: OSI Approved :: Apache Software License
Classifier: Programming Language :: Python :: 3
Classifier: Programming Language :: Python :: 3.7
Classifier: Programming Language :: Python :: 3.8
Classifier: Programming Language :: Python :: 3.9
Classifier: Programming Language :: Python :: 3.10
Classifier: Programming Language :: Python :: 3.11
Classifier: Programming Language :: Python :: 3.12
Classifier: Programming Language :: Python :: 3.13
Requires-Dist: asyncclick (>=8.1.7.2,<9.0.0.0)
Requires-Dist: backoff (>=2.2.1,<3.0.0)
Requires-Dist: dateparser (>=1.2.0,<2.0.0)
Requires-Dist: environs (>=9.5,<10.0)
Requires-Dist: httpx (>=0.28.0,<0.29.0)
Requires-Dist: respx (>=0,<1)
